spytify/__init__.py
spytify/client/__init__.py
spytify/client/base.py
spytify/client/server_client.py
spytify/client/user_client.py
spytify-0.3.2.dist-info/METADATA
spytify-0.3.2.dist-info/WHEEL
spytify-0.3.2.dist-info/licenses/LICENSE
spytify-0.3.2.dist-info/RECORD
