Metadata-Version: 2.4
Name: spytify
Version: 0.3.2
Summary: A minimalistic Spotify API wrapper
Author-email: Rasmus Holmgren <ras.holmgren@gmail.com>
License-File: LICENSE
Classifier: License :: OSI Approved :: MIT License
Classifier: Operating System :: OS Independent
Classifier: Programming Language :: Python :: 3
Requires-Python: >=3.7
